setup.py
dark_bulk_dist/Binomialdistribution.py
dark_bulk_dist/Gaussiandistribution.py
dark_bulk_dist/Generaldistribution.py
dark_bulk_dist/__init__.py
dark_bulk_dist.egg-info/PKG-INFO
dark_bulk_dist.egg-info/SOURCES.txt
dark_bulk_dist.egg-info/dependency_links.txt
dark_bulk_dist.egg-info/not-zip-safe
dark_bulk_dist.egg-info/top_level.txt