Metadata-Version: 1.0
Name: dark-bulk-dist
Version: 1.0
Summary: Gaussian and Binomial distributions
Home-page: UNKNOWN
Author: Dark Bulk
Author-email: darkbulk2016@gmail.com
License: UNKNOWN
Platform: UNKNOWN
